atom2vec/__init__.py
atom2vec/atom_similarity.py
atom2vec-1.1.0.dist-info/METADATA
atom2vec-1.1.0.dist-info/WHEEL
atom2vec-1.1.0.dist-info/top_level.txt
atom2vec-1.1.0.dist-info/RECORD
