Metadata-Version: 2.1
Name: atom2vec
Version: 1.1.0
Summary: A python implement of Atom2Vec: a simple way to describe atoms for machine learning
Author-email: Yuxing Fei <yuxingfei@berkeley.edu>
Project-URL: Repository, https://github.com/idocx/atom2vec
Keywords: material science,machine learning
Requires-Python: >=3.8
Requires-Dist: pymatgen >=2022.0.8
Requires-Dist: scikit-learn >=1.3.2
Requires-Dist: scipy >=1.7.3
